{
  "001@": [
    {
      "0": "11,21-22,24,31,34,39-40,50,60,62-63,65,69-70,72,78,92,110,121,127,132,164,227,274,285,344,370,607,695,754,2001,2003-2012,2014,2016,2018,2020-2021,2025,2031,2038-2039,2042,2044,2049,2055,2093,2106-2107,2153,2270,2351,2434,2505"
    }
  ],
  "001A": [
    {
      "0": "2001:28-05-08"
    }
  ],
  "001B": [
    {
      "0": "BSZ:30-10-24",
      "t": "10:17:54.000"
    }
  ],
  "001D": [
    {
      "0": "0027:25-09-08"
    }
  ],
  "001U": [
    {
      "0": "utf8"
    }
  ],
  "001X": [
    {
      "0": "0"
    }
  ],
  "002@": [
    {
      "0": "Aau"
    }
  ],
  "002C": [
    {
      "a": "Text",
      "b": "txt"
    }
  ],
  "002D": [
    {
      "a": "ohne Hilfsmittel zu benutzen",
      "b": "n"
    }
  ],
  "002E": [
    {
      "a": "Band",
      "b": "nc"
    }
  ],
  "003@": [
    {
      "0": "567022579"
    }
  ],
  "003O": [
    {
      "0": "254925169",
      "a": "OCoLC",
      "v": "2012-12-31"
    }
  ],
  "003S": [
    {
      "0": "282132686"
    }
  ],
  "003T": [
    {
      "0": "254925169",
      "a": "OCoLC"
    },
    {
      "0": "723890428",
      "a": "OCoLC"
    }
  ],
  "004A": [
    {
      "0": "9783476021878",
      "f": "Gb. : ca. sfr 46.00 (freier Pr.), ca. EUR 29.95, ca. EUR 30.80 (AT)"
    }
  ],
  "004L": [
    {
      "0": "9783476021878"
    }
  ],
  "004P": [
    {
      "0": "9783476054692",
      "S": "o"
    }
  ],
  "006G": [
    {
      "0": "988783614"
    }
  ],
  "006U": [
    {
      "0": "08,N23,0178"
    }
  ],
  "006X": [
    {
      "0": "952420360",
      "i": "STBB"
    }
  ],
  "006Y": [
    {
      "0": "STBBT952420360"
    },
    {
      "0": "hks0015584"
    },
    {
      "0": "STBHANTALT988783614"
    },
    {
      "0": "STBHANT006573537"
    }
  ],
  "007G": [
    {
      "0": "988783614",
      "i": "DNB"
    }
  ],
  "009@": [
    {
      "b": "sf"
    },
    {
      "b": "Blocktest"
    }
  ],
  "010@": [
    {
      "a": "ger"
    }
  ],
  "010E": [
    {
      "e": "rda"
    }
  ],
  "011@": [
    {
      "a": "2008",
      "n": "[2008]"
    }
  ],
  "011F": [
    {
      "n": "© 2008"
    }
  ],
  "013D": [
    {
      "3": "209166061",
      "7": "gnd/4066724-8",
      "9": "104682620",
      "V": "Tsvz",
      "a": "Wörterbuch"
    }
  ],
  "017G": [
    {
      "3": "Inhaltstext",
      "5": "01",
      "u": "http://deposit.dnb.de/cgi-bin/dokserv?id=3111295&prov=M&dok_var=1&dok_ext=htm",
      "m": "X: MVB",
      "q": "text/html",
      "v": "20130501",
      "x": "H",
      "A": "DNB",
      "B": "2"
    },
    {
      "3": "Inhaltsverzeichnis",
      "5": "04",
      "S": "0",
      "u": "https://external.dandelon.com/download/attachments/dandelon/ids/DE004ACCB4A77F1AA893DC125750800465391.pdf",
      "m": "X:AGI",
      "q": "pdf/application",
      "v": "2018-06-29",
      "x": "H",
      "A": "GBV",
      "B": "2"
    },
    {
      "3": "Cover",
      "5": "93",
      "u": "https://swbplus.bsz-bw.de/bsz282132686cov.jpg",
      "m": "X:springer",
      "q": "image/jpeg",
      "v": "20160926111535",
      "B": "3"
    },
    {
      "3": "Rezension",
      "5": "07",
      "u": "https://swbplus.bsz-bw.de/bsz282132686rez.htm",
      "m": "V:DE-576;B:ifb",
      "q": "application/pdf",
      "v": "20090326202035",
      "B": "2"
    }
  ],
  "017H": [
    {
      "3": "Auszug",
      "5": "23",
      "u": "https://www.lehmanns.de/media/9285077",
      "x": "H"
    }
  ],
  "019@": [
    {
      "a": "XA-DE-TH"
    }
  ],
  "020I": [
    {
      "a": "Alphabetisch geordnete Begriffe zum abendländischen Denken - von der Antike bis zur Gegenwart - und ausgewählte Stichwörter zur indischen und chinesischen Philosophie. (LK/MA: Altmeyer)"
    }
  ],
  "020K": [
    {
      "a": "Das alphabetisch geordnete Nachschlagewerk mit Begriffen zum abendländischen Denken von der Antike bis zur Gegenwart in einer Neuauflage. Im Vergleich zur Erstausgabe (BA 5/96) sind in diesem Band über 200 Begriffe mehr bearbeitet; die Literaturhinweise sind ergänzt und aktualisiert. - Die Erstausgabe von 1995 sollte ersetzt werden; bei knappen Etats kann die Vorauflage von 1999 (nicht besprochen) weiter im Bestand bleiben. (2 A) (LK/MA: Altmeyer)"
    }
  ],
  "021A": [
    {
      "a": "Metzler Lexikon Philosophie",
      "d": "Begriffe und Definitionen",
      "h": "herausgegeben von Peter Prechtl (†) und Franz-Peter Burkard"
    }
  ],
  "022A": [
    {
      "a": "Metzler Philosophie Lexikon"
    }
  ],
  "027A": [
    {
      "a": "Metzler-Lexikon Philosophie"
    },
    {
      "a": "Metzler-Philosophie-Lexikon"
    }
  ],
  "028C": [
    {
      "3": "292338678",
      "4": "edt",
      "7": "gnd/120687097",
      "9": "080829848",
      "V": "Tpv2",
      "w": "piz",
      "A": "Prechtl",
      "D": "Peter",
      "E": "1948",
      "M": "2007",
      "B": "HerausgeberIn"
    },
    {
      "3": "160488729",
      "4": "edt",
      "7": "gnd/121905586",
      "9": "081611471",
      "V": "Tpv3",
      "w": "piz",
      "A": "Burkard",
      "D": "Franz-Peter",
      "E": "1958",
      "B": "HerausgeberIn"
    }
  ],
  "032@": [
    {
      "a": "3., erweiterte und aktualisierte Auflage"
    }
  ],
  "033A": [
    {
      "p": "Weimar",
      "n": "Verlag J.B. Metzler"
    }
  ],
  "034D": [
    {
      "a": "XV, 705 Seiten"
    }
  ],
  "034I": [
    {
      "a": "24 cm"
    }
  ],
  "037A": [
    {
      "a": "Frühere Auflagen unter dem Titel: Metzler Philosophie Lexikon"
    }
  ],
  "039D": [
    {
      "2": "9783476054692",
      "5": "497151502",
      "9": "1658667204",
      "i": "Erscheint auch als",
      "n": "Online-Ausgabe",
      "R": "Oau",
      "t": "Metzler Lexikon Philosophie",
      "g": "3., erweiterte und aktualisierte Auflage",
      "d": "Stuttgart",
      "e": "J.B. Metzler",
      "f": "2008",
      "h": "1 Online-Ressource (XV, 705 Seiten)"
    }
  ],
  "041A": [
    {
      "3": "209066873",
      "7": "gnd/4045791-6",
      "9": "106200259",
      "V": "Tsvz",
      "a": "Philosophie"
    }
  ],
  "044A": [
    {
      "S": "s",
      "a": "German"
    }
  ],
  "044N": [
    {
      "S": "s",
      "a": "German"
    },
    {
      "S": "s",
      "a": "Philosophie"
    },
    {
      "S": "s",
      "a": "Wörterbuch"
    }
  ],
  "045A": [
    {
      "a": "B43"
    }
  ],
  "045B": [
    {
      "a": "Lal"
    },
    {
      "a": "LAL"
    },
    {
      "a": "PHIL 5"
    },
    {
      "a": "E 100"
    }
  ],
  "045F": [
    {
      "a": "100",
      "A": "BSZ"
    }
  ],
  "045G": [
    {
      "a": "100"
    }
  ],
  "045H": [
    {
      "e": "DDC22ger",
      "a": "103",
      "A": "DDB"
    }
  ],
  "045M": [
    {
      "i": "9",
      "a": "CB 3500"
    }
  ],
  "045Q": [
    {
      "9": "106415239",
      "V": "Tkv",
      "a": "08.00",
      "j": "Philosophie: Allgemeines"
    }
  ],
  "045R": [
    {
      "3": "201265737",
      "7": "rvk/136541:",
      "9": "1271265737",
      "V": "Tkv",
      "a": "PI 2100",
      "j": "Nachschlagewerke",
      "N": "PI 1000-PI 2260",
      "J": "Allgemeines"
    },
    {
      "3": "200638513",
      "7": "rvk/17580:",
      "9": "1270638513",
      "V": "Tkv",
      "a": "CB 3500",
      "j": "Philosophische Nachschlagewerke und Wörterbücher allgemeiner Art",
      "N": "CB 3500-CB 4450",
      "J": "Lexika, Nachschlagewerke, Enzyklopädien, Gesammelte Abhandlungen",
      "A": "DE-24/23sred"
    }
  ],
  "045V": [
    {
      "a": "5,1"
    }
  ],
  "045X": [
    {
      "i": "bicssc",
      "a": "HP",
      "A": "SEPA"
    },
    {
      "i": "bisacsh",
      "a": "PHI000000",
      "A": "SEPA"
    }
  ],
  "046X": [
    {
      "5": "DE-24",
      "a": "aa",
      "f": "PEBW",
      "x": "XA-DE-BW"
    }
  ],
  "047A": [
    {
      "a": "CB 350:L1UB"
    }
  ],
  "047I": [
    {
      "a": "Von der Antike bis zur Gegenwart. Das \"Metzler Lexikon Philosophie\" bietet mehr als 2.200 Begriffe und Definitionen aus dem Bereich der abendländischen, der indischen und der chinesischen Philosophie. Es vermittelt Basiswissen nicht nur für Studenten der Philosophie. Mit über 30 neuen Einträgen aus den Gebieten Bioethik, Philosophie des Geistes, Kognitionswissenschaften, analytische Philosophie und Wissenschaftstheorie."
    }
  ],
  "101@": [
    {
      "a": "11",
      "c": "PICA"
    },
    {
      "a": "21",
      "c": "PICA"
    },
    {
      "a": "22",
      "c": "PICA"
    },
    {
      "a": "24",
      "c": "PICA"
    },
    {
      "a": "31",
      "c": "PICA"
    },
    {
      "a": "34",
      "c": "PICA"
    },
    {
      "a": "39",
      "c": "PICA"
    },
    {
      "a": "40",
      "c": "PICA"
    },
    {
      "a": "50",
      "c": "PICA"
    },
    {
      "a": "60",
      "c": "PICA"
    },
    {
      "a": "62",
      "c": "PICA"
    },
    {
      "a": "63",
      "c": "PICA"
    },
    {
      "a": "65",
      "c": "PICA"
    },
    {
      "a": "69",
      "c": "PICA"
    },
    {
      "a": "70",
      "c": "PICA"
    },
    {
      "a": "72",
      "c": "PICA"
    },
    {
      "a": "78",
      "c": "PICA"
    },
    {
      "a": "92",
      "c": "PICA"
    },
    {
      "a": "121",
      "c": "PICA"
    },
    {
      "a": "127",
      "c": "PICA"
    },
    {
      "a": "132",
      "c": "PICA"
    },
    {
      "a": "227",
      "c": "PICA"
    },
    {
      "a": "274",
      "c": "PICA"
    },
    {
      "a": "285",
      "c": "PICA"
    },
    {
      "a": "370",
      "c": "PICA"
    },
    {
      "a": "607",
      "c": "PICA"
    },
    {
      "a": "695",
      "c": "PICA"
    },
    {
      "a": "754",
      "c": "PICA"
    },
    {
      "a": "2001",
      "c": "PICA"
    },
    {
      "a": "2003",
      "c": "PICA"
    },
    {
      "a": "2004",
      "c": "PICA"
    },
    {
      "a": "2005",
      "c": "PICA"
    },
    {
      "a": "2006",
      "c": "PICA"
    },
    {
      "a": "2007",
      "c": "PICA"
    },
    {
      "a": "2008",
      "c": "PICA"
    },
    {
      "a": "2009",
      "c": "PICA"
    },
    {
      "a": "2010",
      "c": "PICA"
    },
    {
      "a": "2011",
      "c": "PICA"
    },
    {
      "a": "2012",
      "c": "PICA"
    },
    {
      "a": "2014",
      "c": "PICA"
    },
    {
      "a": "2016",
      "c": "PICA"
    },
    {
      "a": "2018",
      "c": "PICA"
    },
    {
      "a": "2020",
      "c": "PICA"
    },
    {
      "a": "2021",
      "c": "PICA"
    },
    {
      "a": "2025",
      "c": "PICA"
    },
    {
      "a": "2031",
      "c": "PICA"
    },
    {
      "a": "2038",
      "c": "PICA"
    },
    {
      "a": "2039",
      "c": "PICA"
    },
    {
      "a": "2042",
      "c": "PICA"
    },
    {
      "a": "2044",
      "c": "PICA"
    },
    {
      "a": "2049",
      "c": "PICA"
    },
    {
      "a": "2055",
      "c": "PICA"
    },
    {
      "a": "2093",
      "c": "PICA"
    },
    {
      "a": "2106",
      "c": "PICA"
    },
    {
      "a": "2107",
      "c": "PICA"
    },
    {
      "a": "2153",
      "c": "PICA"
    },
    {
      "a": "2270",
      "c": "PICA"
    },
    {
      "a": "2351",
      "c": "PICA"
    },
    {
      "a": "2434",
      "c": "PICA"
    },
    {
      "a": "2505",
      "c": "PICA"
    }
  ],
  "101B": [
    {
      "0": "19-09-24",
      "t": "12:32:55.000"
    },
    {
      "0": "08-12-08",
      "t": "11:15:32.000"
    },
    {
      "0": "01-10-08",
      "t": "15:54:39.000"
    },
    {
      "0": "25-02-09",
      "t": "10:35:13.000"
    },
    {
      "0": "29-10-08",
      "t": "16:19:37.000"
    },
    {
      "0": "05-10-11",
      "t": "10:53:57.000"
    },
    {
      "0": "11-06-09",
      "t": "12:38:24.000"
    },
    {
      "0": "20-10-17",
      "t": "15:58:41.000"
    },
    {
      "0": "17-10-21",
      "t": "02:22:17.000"
    }
  ],
  "101U": [
    {
      "0": "utf8"
    },
    {
      "0": "utf8"
    },
    {
      "0": "utf8"
    },
    {
      "0": "utf8"
    },
    {
      "0": "utf8"
    },
    {
      "0": "utf8"
    },
    {
      "0": "utf8"
    },
    {
      "0": "utf8"
    },
    {
      "0": "utf8"
    }
  ],
  "102D": [
    {
      "0": "19-09-24",
      "b": "11",
      "a": "0001"
    },
    {
      "0": "08-12-08",
      "b": "6290",
      "a": "0046"
    },
    {
      "0": "01-10-08",
      "b": "7652",
      "a": "0027"
    },
    {
      "0": "25-02-09",
      "b": "4879",
      "a": "0547"
    },
    {
      "0": "29-10-08",
      "b": "2204",
      "a": "0705"
    },
    {
      "0": "05-10-11",
      "b": "5957",
      "a": "3401"
    },
    {
      "0": "11-06-09",
      "b": "6824",
      "a": "0009"
    },
    {
      "0": "20-10-17",
      "b": "9451",
      "a": "0517"
    },
    {
      "0": "17-10-21",
      "b": "cbs_1536",
      "a": "1999"
    }
  ],
  "145S": [
    {
      "a": "HA 3 Aa 5530",
      "b": "HA 03 Aa 5530"
    },
    {
      "a": "HA 03 Aa 5530 Metzler Lexikon Philosophie : Begriffe und Definitionen / herausgegeben von ... [2008]"
    },
    {
      "a": "HA 03 Aa 5530# L # Metzler Lexikon Philosophie : Begriffe und Definitionen ..."
    },
    {
      "a": "_[ ]103 P923"
    },
    {
      "a": "_[x]2008/2583"
    },
    {
      "a": "_[ ]2008/2583"
    },
    {
      "a": "_[ ]11037829"
    }
  ],
  "201B": [
    {
      "0": "09-03-11",
      "t": "16:05:09.000"
    },
    {
      "0": "28-08-21",
      "t": "21:24:22.000"
    },
    {
      "0": "28-08-21",
      "t": "21:24:22.000"
    },
    {
      "0": "25-08-23",
      "t": "09:53:31.000"
    },
    {
      "0": "11-06-24",
      "t": "14:19:49.000"
    },
    {
      "0": "27-02-24",
      "t": "18:04:19.000"
    },
    {
      "0": "09-10-08",
      "t": "12:45:20.000"
    },
    {
      "0": "04-08-10",
      "t": "11:23:29.000"
    },
    {
      "0": "11-02-09",
      "t": "10:54:42.000"
    },
    {
      "0": "01-07-21",
      "t": "11:52:27.000"
    },
    {
      "0": "16-03-22",
      "t": "13:18:25.000"
    },
    {
      "0": "05-04-11",
      "t": "16:46:01.000"
    },
    {
      "0": "28-09-16",
      "t": "09:15:49.000"
    },
    {
      "0": "29-10-08",
      "t": "16:19:37.000"
    },
    {
      "0": "11-12-17",
      "t": "18:16:35.000"
    },
    {
      "0": "06-10-08",
      "t": "13:13:49.000"
    },
    {
      "0": "02-04-21",
      "t": "23:07:37.000"
    },
    {
      "0": "17-09-24",
      "t": "09:17:14.000"
    },
    {
      "0": "03-12-08",
      "t": "14:39:02.000"
    },
    {
      "0": "24-11-15",
      "t": "19:00:26.000"
    },
    {
      "0": "17-10-19",
      "t": "14:28:07.000"
    },
    {
      "0": "12-02-20",
      "t": "15:25:26.000"
    },
    {
      "0": "14-06-23",
      "t": "02:32:06.000"
    },
    {
      "0": "14-06-23",
      "t": "02:32:06.000"
    },
    {
      "0": "08-07-21",
      "t": "00:54:24.000"
    },
    {
      "0": "05-01-23",
      "t": "06:46:57.000"
    },
    {
      "0": "07-04-15",
      "t": "11:44:49.000"
    },
    {
      "0": "24-10-17",
      "t": "10:37:21.000"
    },
    {
      "0": "20-01-09",
      "t": "14:53:34.000"
    },
    {
      "0": "19-06-12",
      "t": "15:17:16.000"
    },
    {
      "0": "28-06-13",
      "t": "03:41:59.000"
    },
    {
      "0": "03-11-17",
      "t": "13:24:11.000"
    },
    {
      "0": "25-09-20",
      "t": "13:28:51.000"
    },
    {
      "0": "06-04-23",
      "t": "15:02:10.000"
    },
    {
      "0": "18-03-15",
      "t": "17:20:18.000"
    },
    {
      "0": "03-08-22",
      "t": "23:13:47.000"
    },
    {
      "0": "15-09-08",
      "t": "08:19:53.000"
    },
    {
      "0": "22-09-08",
      "t": "10:28:02.000"
    },
    {
      "0": "02-02-09",
      "t": "10:25:09.000"
    },
    {
      "0": "14-07-09",
      "t": "15:06:35.000"
    },
    {
      "0": "01-03-18",
      "t": "09:11:27.000"
    },
    {
      "0": "17-10-13",
      "t": "08:54:24.000"
    },
    {
      "0": "30-08-12",
      "t": "16:23:53.000"
    },
    {
      "0": "07-01-09",
      "t": "10:33:53.000"
    },
    {
      "0": "19-09-08",
      "t": "12:36:40.000"
    },
    {
      "0": "12-11-20",
      "t": "08:17:06.000"
    },
    {
      "0": "22-03-21",
      "t": "05:55:15.000"
    },
    {
      "0": "22-03-21",
      "t": "05:55:15.000"
    },
    {
      "0": "22-03-21",
      "t": "06:04:28.000"
    },
    {
      "0": "23-09-08",
      "t": "14:23:36.000"
    },
    {
      "0": "27-03-09",
      "t": "10:41:19.000"
    },
    {
      "0": "28-03-09",
      "t": "02:05:00.000"
    },
    {
      "0": "09-05-14",
      "t": "18:16:38.000"
    },
    {
      "0": "19-04-10",
      "t": "14:21:27.000"
    },
    {
      "0": "12-12-11",
      "t": "14:03:47.000"
    },
    {
      "0": "08-07-24",
      "t": "22:06:25.000"
    },
    {
      "0": "03-09-20",
      "t": "10:58:31.000"
    },
    {
      "0": "06-10-08",
      "t": "15:31:31.000"
    },
    {
      "0": "07-01-09",
      "t": "17:40:55.000"
    },
    {
      "0": "13-12-18",
      "t": "14:12:04.000"
    },
    {
      "0": "03-07-23",
      "t": "09:31:23.000"
    },
    {
      "0": "22-12-09",
      "t": "10:25:45.000"
    },
    {
      "0": "22-02-22",
      "t": "14:09:33.000"
    },
    {
      "0": "23-11-11",
      "t": "10:53:44.000"
    },
    {
      "0": "12-04-24",
      "t": "15:43:19.000"
    },
    {
      "0": "19-09-24",
      "t": "22:18:02.000"
    },
    {
      "0": "19-09-24",
      "t": "22:19:24.000"
    },
    {
      "0": "26-01-18",
      "t": "15:51:43.000"
    },
    {
      "0": "24-10-08",
      "t": "10:37:14.000"
    },
    {
      "0": "21-01-19",
      "t": "11:01:29.000"
    },
    {
      "0": "17-12-08",
      "t": "15:18:27.000"
    },
    {
      "0": "09-04-09",
      "t": "11:58:44.000"
    },
    {
      "0": "04-12-24",
      "t": "12:46:40.000"
    },
    {
      "0": "10-10-17",
      "t": "17:28:53.000"
    },
    {
      "0": "19-10-10",
      "t": "11:50:06.000"
    },
    {
      "0": "28-07-09",
      "t": "15:40:21.000"
    },
    {
      "0": "01-03-10",
      "t": "13:51:01.000"
    },
    {
      "0": "27-10-21",
      "t": "13:07:40.000"
    },
    {
      "0": "23-07-15",
      "t": "19:33:25.000"
    }
  ],
  "201U": [
    {
      "0": "utf8"
    },
    {
      "0": "utf8"
    },
    {
      "0": "utf8"
    },
    {
      "0": "utf8"
    },
    {
      "0": "utf8"
    },
    {
      "0": "utf8"
    },
    {
      "0": "utf8"
    },
    {
      "0": "utf8"
    },
    {
      "0": "utf8"
    },
    {
      "0": "utf8"
    },
    {
      "0": "utf8"
    },
    {
      "0": "utf8"
    },
    {
      "0": "utf8"
    },
    {
      "0": "utf8"
    },
    {
      "0": "utf8"
    },
    {
      "0": "utf8"
    },
    {
      "0": "utf8"
    },
    {
      "0": "utf8"
    },
    {
      "0": "utf8"
    },
    {
      "0": "utf8"
    },
    {
      "0": "utf8"
    },
    {
      "0": "utf8"
    },
    {
      "0": "utf8"
    },
    {
      "0": "utf8"
    },
    {
      "0": "utf8"
    },
    {
      "0": "utf8"
    },
    {
      "0": "utf8"
    },
    {
      "0": "utf8"
    },
    {
      "0": "utf8"
    },
    {
      "0": "utf8"
    },
    {
      "0": "utf8"
    },
    {
      "0": "utf8"
    },
    {
      "0": "utf8"
    },
    {
      "0": "utf8"
    },
    {
      "0": "utf8"
    },
    {
      "0": "utf8"
    },
    {
      "0": "utf8"
    },
    {
      "0": "utf8"
    },
    {
      "0": "utf8"
    },
    {
      "0": "utf8"
    },
    {
      "0": "utf8"
    },
    {
      "0": "utf8"
    },
    {
      "0": "utf8"
    },
    {
      "0": "utf8"
    },
    {
      "0": "utf8"
    },
    {
      "0": "utf8"
    },
    {
      "0": "utf8"
    },
    {
      "0": "utf8"
    },
    {
      "0": "utf8"
    },
    {
      "0": "utf8"
    },
    {
      "0": "utf8"
    },
    {
      "0": "utf8"
    },
    {
      "0": "utf8"
    },
    {
      "0": "utf8"
    },
    {
      "0": "utf8"
    },
    {
      "0": "utf8"
    },
    {
      "0": "utf8"
    },
    {
      "0": "utf8"
    },
    {
      "0": "utf8"
    },
    {
      "0": "utf8"
    },
    {
      "0": "utf8"
    },
    {
      "0": "utf8"
    },
    {
      "0": "utf8"
    },
    {
      "0": "utf8"
    },
    {
      "0": "utf8"
    },
    {
      "0": "utf8"
    },
    {
      "0": "utf8"
    },
    {
      "0": "utf8"
    },
    {
      "0": "utf8"
    },
    {
      "0": "utf8"
    },
    {
      "0": "utf8"
    },
    {
      "0": "utf8"
    },
    {
      "0": "utf8"
    },
    {
      "0": "utf8"
    },
    {
      "0": "utf8"
    },
    {
      "0": "utf8"
    },
    {
      "0": "utf8"
    },
    {
      "0": "utf8"
    },
    {
      "0": "utf8"
    }
  ],
  "202D": [
    {
      "0": "09-03-11",
      "b": "1685",
      "a": "0001"
    },
    {
      "0": "28-08-21",
      "b": "r1533",
      "a": "1999"
    },
    {
      "0": "28-08-21",
      "b": "r1533",
      "a": "1999"
    },
    {
      "0": "25-08-23",
      "b": "r1745",
      "a": "1999"
    },
    {
      "0": "11-06-24",
      "b": "7457",
      "a": "0008"
    },
    {
      "0": "27-02-24",
      "b": "6393",
      "a": "0008/0037"
    },
    {
      "0": "09-10-08",
      "b": "5675",
      "a": "0027"
    },
    {
      "0": "04-08-10",
      "b": "7651",
      "a": "0027"
    },
    {
      "0": "11-02-09",
      "b": "6886",
      "a": "3551"
    },
    {
      "0": "01-07-21",
      "b": "5794",
      "a": "0547"
    },
    {
      "0": "16-03-22",
      "b": "1336",
      "a": "0007"
    },
    {
      "0": "05-04-11",
      "b": "1793",
      "a": "0007"
    },
    {
      "0": "28-09-16",
      "b": "2047",
      "a": "0023"
    },
    {
      "0": "29-10-08",
      "b": "2204",
      "a": "0705"
    },
    {
      "0": "11-12-17",
      "b": "4434",
      "a": "0028"
    },
    {
      "0": "06-10-08",
      "b": "4432",
      "a": "0028"
    },
    {
      "0": "02-04-21",
      "b": "r1471",
      "a": "1999"
    },
    {
      "0": "17-09-24",
      "b": "2517",
      "a": "0003/0010"
    },
    {
      "0": "03-12-08",
      "b": "2474",
      "a": "0003/0010"
    },
    {
      "0": "24-11-15",
      "b": "r69umzug8",
      "a": "1999"
    },
    {
      "0": "17-10-19",
      "b": "3356",
      "a": "0089"
    },
    {
      "0": "12-02-20",
      "b": "3063",
      "a": "0035"
    },
    {
      "0": "14-06-23",
      "b": "csf_mm_ki",
      "a": "1999"
    },
    {
      "0": "14-06-23",
      "b": "csf_mm_ki",
      "a": "1999"
    },
    {
      "0": "08-07-21",
      "b": "r1528",
      "a": "1999"
    },
    {
      "0": "05-01-23",
      "b": "genloc4alma_k10plus",
      "a": "0045"
    },
    {
      "0": "07-04-15",
      "b": "7909",
      "a": "3564"
    },
    {
      "0": "24-10-17",
      "b": "5517",
      "a": "0959/0004"
    },
    {
      "0": "20-01-09",
      "b": "4772",
      "a": "0056"
    },
    {
      "0": "19-06-12",
      "b": "4776",
      "a": "0056"
    },
    {
      "0": "28-06-13",
      "b": "stbblok",
      "a": "0478"
    },
    {
      "0": "03-11-17",
      "b": "9462",
      "a": "0517"
    },
    {
      "0": "25-09-20",
      "b": "844597",
      "a": "4370"
    },
    {
      "0": "06-04-23",
      "b": "927797",
      "a": "4607"
    },
    {
      "0": "08-06-15",
      "b": "csf_mm_vzg",
      "a": "1999"
    },
    {
      "0": "03-08-22",
      "b": "r1655",
      "a": "1999"
    },
    {
      "0": "12-11-20",
      "b": "touchtitle_jg",
      "a": "20728"
    },
    {
      "0": "04-12-24",
      "b": "csf_elvis__offline",
      "a": "20728"
    }
  ],
  "203@": [
    {
      "0": "896958655"
    },
    {
      "0": "911210881"
    },
    {
      "0": "914036041"
    },
    {
      "0": "89677130X"
    },
    {
      "0": "911240411"
    },
    {
      "0": "1616915943"
    },
    {
      "0": "888801548"
    },
    {
      "0": "1174849967"
    },
    {
      "0": "916697754"
    },
    {
      "0": "921836406"
    },
    {
      "0": "913571857"
    },
    {
      "0": "1233416316"
    },
    {
      "0": "1624880762"
    },
    {
      "0": "895014645"
    },
    {
      "0": "88121714X"
    },
    {
      "0": "893597651"
    },
    {
      "0": "1267583460"
    },
    {
      "0": "892838329"
    },
    {
      "0": "913530557"
    },
    {
      "0": "936059915"
    },
    {
      "0": "910637156"
    },
    {
      "0": "3487102269"
    },
    {
      "0": "4335838069"
    },
    {
      "0": "4335838077"
    },
    {
      "0": "883071592"
    },
    {
      "0": "91069639X"
    },
    {
      "0": "1270888811"
    },
    {
      "0": "1716129753"
    },
    {
      "0": "915398028"
    },
    {
      "0": "1308365675"
    },
    {
      "0": "1403898170"
    },
    {
      "0": "1717158390"
    },
    {
      "0": "117644543X"
    },
    {
      "0": "1307422047"
    },
    {
      "0": "1545059071"
    },
    {
      "0": "1225146135"
    },
    {
      "0": "3176697864"
    },
    {
      "0": "3176697899"
    },
    {
      "0": "3176697996"
    },
    {
      "0": "3176698062"
    },
    {
      "0": "3176698089"
    },
    {
      "0": "3176698186"
    },
    {
      "0": "3176698194"
    },
    {
      "0": "3176698313"
    },
    {
      "0": "3176698429"
    },
    {
      "0": "3176698526"
    },
    {
      "0": "3176698585"
    },
    {
      "0": "3176698593"
    },
    {
      "0": "3176698607"
    },
    {
      "0": "3176698682"
    },
    {
      "0": "3176698712"
    },
    {
      "0": "317669878X"
    },
    {
      "0": "3176698801"
    },
    {
      "0": "317669881X"
    },
    {
      "0": "3176698828"
    },
    {
      "0": "3176698895"
    },
    {
      "0": "3746237300"
    },
    {
      "0": "317669900X"
    },
    {
      "0": "3176699077"
    },
    {
      "0": "3176699158"
    },
    {
      "0": "3176699255"
    },
    {
      "0": "3176699328"
    },
    {
      "0": "3176699417"
    },
    {
      "0": "3176699484"
    },
    {
      "0": "3176699565"
    },
    {
      "0": "3176699581"
    },
    {
      "0": "3770107284"
    },
    {
      "0": "3176699670"
    },
    {
      "0": "317669976X"
    },
    {
      "0": "3176699875"
    },
    {
      "0": "3176699956"
    },
    {
      "0": "3176699980"
    },
    {
      "0": "3176700075"
    },
    {
      "0": "3176700113"
    },
    {
      "0": "3176700245"
    },
    {
      "0": "3176700334"
    },
    {
      "0": "3176700415"
    },
    {
      "0": "399677351X"
    },
    {
      "0": "3176700512"
    }
  ],
  "208@": [
    {
      "a": "22-10-08",
      "b": "k"
    },
    {
      "a": "05-12-08",
      "b": "zza"
    },
    {
      "a": "05-12-08",
      "b": "zza"
    },
    {
      "a": "21-10-08",
      "b": "zi30908"
    },
    {
      "a": "24-11-08",
      "b": "zz1"
    },
    {
      "a": "26-05-16",
      "b": "zf037"
    },
    {
      "a": "25-09-08",
      "b": "z"
    },
    {
      "a": "02-08-10",
      "b": "z"
    },
    {
      "a": "11-02-09",
      "b": "zi007"
    },
    {
      "a": "25-02-09",
      "b": "zet1"
    },
    {
      "a": "20-01-09",
      "b": "xsn"
    },
    {
      "a": "05-04-11",
      "b": "zi052"
    },
    {
      "a": "27-07-16",
      "b": "k"
    },
    {
      "a": "29-10-08",
      "b": "z"
    },
    {
      "a": "08-07-08",
      "b": "z"
    },
    {
      "a": "08-07-08",
      "b": "z"
    },
    {
      "a": "20-10-11",
      "b": "zf"
    },
    {
      "a": "02-10-08",
      "b": "za179"
    },
    {
      "a": "03-12-08",
      "b": "za010"
    },
    {
      "a": "11-06-09",
      "b": "zi224"
    },
    {
      "a": "18-11-08",
      "b": "zsa"
    },
    {
      "a": "14-06-19",
      "b": "kz"
    },
    {
      "a": "27-04-20",
      "b": "n"
    },
    {
      "a": "27-04-20",
      "b": "n"
    },
    {
      "a": "08-10-08",
      "b": "zn"
    },
    {
      "a": "19-11-08",
      "b": "z"
    },
    {
      "a": "29-09-11",
      "b": "zt25801"
    },
    {
      "a": "19-10-17",
      "b": "kl"
    },
    {
      "a": "17-12-08",
      "b": "x"
    },
    {
      "a": "13-06-12",
      "b": "x"
    },
    {
      "a": "28-06-13",
      "b": "n"
    },
    {
      "a": "20-10-17",
      "b": "z"
    },
    {
      "a": "13-08-10",
      "b": "z"
    },
    {
      "a": "05-06-12",
      "b": "z"
    },
    {
      "a": "18-03-15",
      "b": "n"
    },
    {
      "a": "01-05-10",
      "b": "n"
    },
    {
      "a": "01-07-08",
      "b": "l01"
    },
    {
      "a": "22-09-08",
      "b": "l02"
    },
    {
      "a": "11-12-08",
      "b": "l01"
    },
    {
      "a": "10-06-09",
      "b": "l01"
    },
    {
      "a": "01-03-18",
      "b": "l01"
    },
    {
      "a": "13-11-09",
      "b": "l01"
    },
    {
      "a": "23-06-10",
      "b": "l01"
    },
    {
      "a": "11-12-08",
      "b": "l01"
    },
    {
      "a": "26-08-08",
      "b": "l01"
    },
    {
      "a": "29-09-08",
      "b": "l01"
    },
    {
      "a": "02-03-16",
      "b": "l01"
    },
    {
      "a": "02-03-16",
      "b": "l01"
    },
    {
      "a": "25-03-16",
      "b": "l01"
    },
    {
      "a": "11-08-08",
      "b": "l01"
    },
    {
      "a": "23-09-08",
      "b": "l01"
    },
    {
      "a": "13-10-08",
      "b": "l01"
    },
    {
      "a": "23-07-09",
      "b": "l01"
    },
    {
      "a": "12-04-10",
      "b": "l01"
    },
    {
      "a": "29-11-11",
      "b": "l01"
    },
    {
      "a": "10-11-08",
      "b": "l01"
    },
    {
      "a": "03-09-20",
      "b": "l01"
    },
    {
      "a": "29-09-08",
      "b": "l01"
    },
    {
      "a": "17-11-08",
      "b": "l01"
    },
    {
      "a": "13-12-18",
      "b": "l01"
    },
    {
      "a": "08-10-08",
      "b": "l01"
    },
    {
      "a": "22-12-09",
      "b": "l01"
    },
    {
      "a": "08-02-12",
      "b": "l01"
    },
    {
      "a": "15-11-11",
      "b": "l01"
    },
    {
      "a": "13-11-18",
      "b": "l01"
    },
    {
      "a": "11-12-18",
      "b": "l01"
    },
    {
      "a": "06-10-20",
      "b": "l01"
    },
    {
      "a": "26-01-18",
      "b": "l01"
    },
    {
      "a": "13-10-08",
      "b": "l01"
    },
    {
      "a": "08-01-19",
      "b": "l01"
    },
    {
      "a": "17-12-08",
      "b": "l01"
    },
    {
      "a": "07-04-09",
      "b": "l01"
    },
    {
      "a": "22-09-17",
      "b": "l01"
    },
    {
      "a": "13-09-12",
      "b": "l01"
    },
    {
      "a": "18-01-10",
      "b": "l01"
    },
    {
      "a": "28-07-09",
      "b": "l01"
    },
    {
      "a": "01-03-10",
      "b": "l01"
    },
    {
      "a": "27-10-21",
      "b": "l01"
    },
    {
      "a": "10-07-15",
      "b": "l01"
    }
  ],
  "209A": [
    {
      "f": "1:HA3",
      "a": "HA 3 Aa 5530",
      "d": "s",
      "x": "00"
    },
    {
      "a": "1 A 706238",
      "x": "09"
    },
    {
      "f": "E03",
      "a": "h phi 001 b/362",
      "d": "d",
      "x": "00"
    },
    {
      "f": "E03",
      "a": "a phi 001 b/362a",
      "d": "u",
      "x": "00"
    },
    {
      "f": "18/309-PH",
      "a": "Z 1494b",
      "d": "c",
      "x": "00"
    },
    {
      "f": "18/309-p",
      "a": "Z 1494b",
      "d": "i",
      "x": "04"
    },
    {
      "b": "8",
      "f": "10 phi 270",
      "a": "At 316 3. Aufl.",
      "d": "i",
      "x": "00"
    },
    {
      "f": "8/37",
      "a": "X 61",
      "d": "i",
      "x": "00"
    },
    {
      "f": "J 30",
      "a": "PHI:AB:150:Pre::2008",
      "d": "i",
      "x": "00"
    },
    {
      "f": "J 30",
      "a": "PHI:AB:150:Pre::2008",
      "d": "i",
      "x": "00"
    },
    {
      "f": "18/287",
      "a": "So.16.Met.3.A",
      "d": "i",
      "x": "00"
    },
    {
      "f": "LS",
      "a": "CB 3500 P923(3)",
      "d": "b",
      "x": "00"
    },
    {
      "f": "MAG-EXZ16",
      "a": "D 000 = 2008 A 19685",
      "d": "u",
      "x": "00"
    },
    {
      "f": "EXZ-16",
      "a": "D 000 = 2008 A 19685",
      "x": "05"
    },
    {
      "a": "2008 A 19685",
      "x": "09"
    },
    {
      "f": "7/052",
      "a": "A-3 3/42 3.A.",
      "d": "i",
      "x": "00"
    },
    {
      "a": "PH 01-1057",
      "d": "i",
      "x": "00"
    },
    {
      "a": "66.2880",
      "x": "09"
    },
    {
      "f": "PAE",
      "a": "PHL 001:YA0012(003)",
      "d": "u",
      "x": "00"
    },
    {
      "f": "28/BB2-PHI",
      "a": "CB 3500 P923(3)",
      "d": "u",
      "x": "00"
    },
    {
      "f": "28/BB2-KAT",
      "a": "CB 3500 P923(3)",
      "d": "s",
      "x": "00"
    },
    {
      "f": "F-1",
      "a": "Ba 0024/21",
      "d": "g",
      "x": "00"
    },
    {
      "a": "249 567",
      "x": "09"
    },
    {
      "b": "3",
      "j": "179",
      "f": "Ha 179-RVK",
      "a": "CB 3500 113 3.",
      "d": "i",
      "x": "00"
    },
    {
      "b": "3",
      "j": "179",
      "f": "Ha 179",
      "a": "Phi 1 Met",
      "x": "09"
    },
    {
      "b": "3",
      "j": "10",
      "f": "Ha 10",
      "a": "E E 020",
      "d": "i",
      "x": "00"
    },
    {
      "f": "BB 310",
      "a": "310/CB 3500 P923(3)",
      "d": "c",
      "x": "00"
    },
    {
      "b": "89",
      "j": "19",
      "B": "89",
      "f": "FBS",
      "a": "AA 60 21(3)",
      "d": "i",
      "x": "00"
    },
    {
      "B": "35",
      "f": "ZEN",
      "a": "2019/5328",
      "d": "u",
      "x": "00"
    },
    {
      "b": "0115",
      "e": "1",
      "f": "Stadtbibliothek",
      "a": "Phil 5/39 c",
      "d": "u",
      "x": "00"
    },
    {
      "b": "0115",
      "e": "1",
      "f": "STB Linden",
      "a": "Phil 5",
      "d": "u",
      "x": "00"
    },
    {
      "f": "INF",
      "a": "08.00 = 44 A 1926",
      "d": "i",
      "x": "00"
    },
    {
      "a": "LS: Phil 006/22 08-8138",
      "d": "s",
      "x": "00"
    },
    {
      "f": "18/258-OG2i",
      "a": "Lal, Prech, Metz",
      "d": "i",
      "x": "00"
    },
    {
      "b": "0959",
      "j": "4",
      "f": "L",
      "a": "HIA 15/3",
      "d": "u",
      "x": "00"
    },
    {
      "a": "Lal Met",
      "d": "c",
      "x": "00"
    },
    {
      "f": "LS",
      "a": "Ls XI b 14",
      "d": "i",
      "x": "00"
    },
    {
      "f": "10/22",
      "a": "Phil 5 M",
      "d": "u",
      "x": "00"
    },
    {
      "f": "4001",
      "a": "CB 3500 PRE",
      "d": "s",
      "x": "00"
    },
    {
      "f": "EG",
      "a": "CB 3500 001",
      "d": "i",
      "x": "00"
    },
    {
      "a": "GKE-103",
      "x": "01"
    },
    {
      "a": "lex/Phi/22",
      "d": "i",
      "x": "00"
    },
    {
      "b": "1911",
      "a": "PHI-Met-2008",
      "d": "u",
      "x": "00"
    },
    {
      "f": "Ref",
      "a": "103 P923",
      "d": "s",
      "x": "00"
    },
    {
      "a": "2008/2583",
      "x": "01"
    },
    {
      "B": "21",
      "f": "LS",
      "a": "48 A 10122",
      "D": "p",
      "x": "00"
    },
    {
      "a": "philos A 230",
      "x": "01"
    },
    {
      "B": "21",
      "f": "Lehrbuchsammlung",
      "a": "philos A 9 Auflage 3",
      "x": "00"
    },
    {
      "B": "25",
      "a": "LS: Phil 1,C 4",
      "D": "p",
      "x": "00"
    },
    {
      "B": "25/156",
      "a": "Frei 156",
      "D": "p",
      "x": "00"
    },
    {
      "a": "PHIL A-3/89",
      "x": "01"
    },
    {
      "B": "25/38",
      "a": "Frei 38: Phil Allg/496",
      "D": "p",
      "x": "00"
    },
    {
      "B": "Sa 16",
      "a": "CB 3500 Met 3. Aufl.",
      "D": "p",
      "x": "00"
    },
    {
      "B": "291",
      "a": "02/CB 3500 P923(3)",
      "J": "n",
      "x": "00"
    },
    {
      "B": "14",
      "x": "00"
    },
    {
      "B": "352",
      "x": "00"
    },
    {
      "B": "24",
      "a": "58/13209",
      "D": "p",
      "x": "00"
    },
    {
      "f": "Freihand Präsenzbestand",
      "g": "CB 3500 P923",
      "x": "01"
    },
    {
      "B": "180",
      "f": "110",
      "a": "110 CB 3500 P923",
      "J": "n",
      "x": "00"
    },
    {
      "B": "180",
      "f": "500",
      "a": "500 CB 3500 P923(3)",
      "J": "n",
      "x": "00"
    },
    {
      "B": "180",
      "f": "WEST_EG",
      "a": " 120 CB 3500 P923 ",
      "J": "n",
      "x": "00"
    },
    {
      "B": "15",
      "x": "00"
    },
    {
      "B": "16",
      "a": "LA-C3-22211",
      "l": "(3)",
      "x": "00"
    },
    {
      "B": "16/12",
      "a": "503 Pre 1a",
      "D": "p",
      "x": "00"
    },
    {
      "B": "16/13",
      "f": "355",
      "a": "JU/PI 2100 P923(3)",
      "D": "p",
      "x": "00"
    },
    {
      "B": "16/29",
      "a": "Phil 1 PRE 66/1 a",
      "D": "p",
      "x": "00"
    },
    {
      "B": "16/152",
      "a": "A 11513.2",
      "D": "p",
      "x": "00"
    },
    {
      "B": "90",
      "a": "96 A 918(3)",
      "D": "n",
      "x": "00"
    },
    {
      "B": "93/106",
      "a": "Ad 3 Prech 1",
      "D": "p",
      "x": "00"
    },
    {
      "B": "31",
      "a": "108 A 54040",
      "D": "p",
      "x": "00"
    },
    {
      "a": "LS: Ca00006b",
      "x": "01"
    },
    {
      "B": "Ch 1",
      "a": "$BCh 1",
      "x": "00"
    },
    {
      "B": "289",
      "a": "WZ 13.3/2008 P",
      "J": "l",
      "x": "00"
    },
    {
      "B": "Frei 129",
      "a": "CB 3500 P923 (3)",
      "J": "n",
      "x": "00"
    },
    {
      "B": "Lg 1",
      "a": "Phil 1a Met",
      "x": "00"
    },
    {
      "B": "752",
      "a": "L al/ Metz 26",
      "J": "n",
      "x": "00"
    },
    {
      "B": "He 76",
      "a": "D 1/45",
      "D": "p",
      "x": "00"
    },
    {
      "B": "M 504183",
      "J": "n",
      "x": "00"
    },
    {
      "B": "M 504160",
      "J": "n",
      "x": "00"
    },
    {
      "B": "M 504202",
      "J": "n",
      "x": "00"
    },
    {
      "B": "751",
      "J": "l",
      "x": "00"
    },
    {
      "B": "Frei 26",
      "a": "LS: C 2 a",
      "D": "p",
      "x": "00"
    },
    {
      "a": "HH 9911",
      "x": "01"
    },
    {
      "B": "840/3",
      "a": "CB 3500 P923 (2008)",
      "J": "l",
      "x": "00"
    },
    {
      "B": "Mh 39",
      "D": "p",
      "J": "n",
      "x": "00"
    },
    {
      "B": "Mh 39",
      "a": "CA 749/2. Aufl.",
      "D": "p",
      "x": "00"
    },
    {
      "B": "Stg 259",
      "J": "k",
      "x": "00"
    },
    {
      "B": "Frei 160",
      "a": "A11 15,3",
      "D": "p",
      "x": "00"
    },
    {
      "B": "Hed 2/2",
      "a": "E 000/ Metz",
      "D": "p",
      "x": "00"
    },
    {
      "B": "Tü 128",
      "a": "Phil-p 21",
      "D": "p",
      "x": "00"
    },
    {
      "B": "581",
      "a": "PHIL 1 Met",
      "D": "p",
      "x": "00"
    },
    {
      "B": "Ess 7",
      "J": "n",
      "x": "00"
    },
    {
      "B": "B 478",
      "x": "00"
    }
  ],
  "209G": [
    {
      "a": "154090155010"
    },
    {
      "a": "46$0000734411"
    },
    {
      "a": "46$0000734438"
    },
    {
      "a": "102293711"
    },
    {
      "a": "8$0005197058"
    },
    {
      "a": "8$0006697658"
    },
    {
      "a": "27$022268375"
    },
    {
      "a": "27$025524534"
    },
    {
      "a": "SP053110"
    },
    {
      "a": "547$20004513X"
    },
    {
      "a": "7$222099186"
    },
    {
      "a": "23$13647288"
    },
    {
      "a": "705/0$24182427"
    },
    {
      "a": "28$012130613"
    },
    {
      "a": "28$012130605"
    },
    {
      "a": "WIM2$004786580"
    },
    {
      "a": "3/179$00331007"
    },
    {
      "a": "3/44$001364251"
    },
    {
      "a": "9$0797373X"
    },
    {
      "a": "89$124498884"
    },
    {
      "a": "35$038742160"
    },
    {
      "a": "33$001975412"
    },
    {
      "a": "45$1902569X"
    },
    {
      "a": "0000524092"
    },
    {
      "a": "959$2952580"
    },
    {
      "a": "91705687876"
    },
    {
      "a": "91708272233"
    },
    {
      "a": "16029188"
    },
    {
      "a": "HC020094"
    },
    {
      "a": "4607$0604623"
    },
    {
      "a": "200002088"
    },
    {
      "a": "11037829"
    },
    {
      "a": "200879724"
    },
    {
      "a": "613933304"
    },
    {
      "a": "616428731"
    },
    {
      "a": "602994319"
    },
    {
      "a": "370050238"
    },
    {
      "a": "49179291031"
    },
    {
      "a": "00000056"
    }
  ],
  "220E": [
    {
      "a": "HA3",
      "b": "2bWa",
      "c": "ersetzt ältere Aufl."
    }
  ],
  "220J": [
    {
      "b": "L",
      "y": "Im LS verfuegbar",
      "a": "02-12-08",
      "c": "1685"
    }
  ],
  "145Z": [
    {
      "a": "phi 001 b"
    },
    {
      "a": "61"
    },
    {
      "a": "PHI:AB:150:"
    },
    {
      "a": "CB 3500"
    },
    {
      "a": "PHL 001"
    },
    {
      "a": "WE"
    },
    {
      "a": "Ba 0024"
    },
    {
      "a": "CB 3500"
    },
    {
      "a": "CB 3500"
    },
    {
      "a": "PI 2100"
    }
  ],
  "209C": [
    {
      "a": "xj 6158",
      "x": "00"
    },
    {
      "a": "xj 6159",
      "x": "00"
    },
    {
      "a": "077 2008/2206",
      "x": "00"
    },
    {
      "a": "30877",
      "x": "00"
    },
    {
      "a": "C 15316",
      "x": "00"
    },
    {
      "a": "U 114388",
      "x": "00"
    },
    {
      "a": "09.41",
      "x": "00"
    },
    {
      "a": "2009006325",
      "x": "00"
    },
    {
      "a": "11.0499",
      "x": "00"
    },
    {
      "a": "66/002880",
      "x": "00"
    },
    {
      "a": "2008 10793",
      "x": "00"
    },
    {
      "a": "2008.19116",
      "x": "00"
    },
    {
      "a": "2008.19117",
      "x": "00"
    },
    {
      "a": "179/2008/00183",
      "x": "00"
    },
    {
      "a": "10E/2003/02078/01",
      "x": "00"
    },
    {
      "a": "2009.7044",
      "x": "00"
    },
    {
      "a": "FBS 2008-2491",
      "x": "00"
    },
    {
      "a": "35$038742160",
      "x": "00"
    },
    {
      "a": "2011:1520",
      "x": "00"
    },
    {
      "a": "018670",
      "x": "00"
    },
    {
      "a": "12.894",
      "x": "00"
    },
    {
      "a": "16029188",
      "x": "00"
    },
    {
      "a": "2010-1276",
      "x": "00"
    },
    {
      "a": "2008/2583",
      "x": "00"
    },
    {
      "a": "PI-0800334",
      "x": "00"
    },
    {
      "a": "SG-1000140",
      "x": "00"
    },
    {
      "a": "IR-1100206",
      "x": "00"
    },
    {
      "a": "B 08/2055",
      "x": "00"
    },
    {
      "a": "39 920",
      "x": "00"
    }
  ],
  "201A": [
    {
      "0": "11-06-24"
    },
    {
      "0": "27-02-24"
    },
    {
      "0": "17-09-24"
    },
    {
      "0": "14-06-19"
    },
    {
      "0": "14-06-23"
    },
    {
      "0": "14-06-23"
    },
    {
      "0": "01-07-08"
    },
    {
      "0": "22-09-08"
    },
    {
      "0": "11-12-08"
    },
    {
      "0": "10-06-09"
    },
    {
      "0": "01-03-18"
    },
    {
      "0": "13-11-09"
    },
    {
      "0": "23-06-10"
    },
    {
      "0": "11-12-08"
    },
    {
      "0": "26-08-08"
    },
    {
      "0": "29-09-08"
    },
    {
      "0": "02-03-16"
    },
    {
      "0": "02-03-16"
    },
    {
      "0": "25-03-16"
    },
    {
      "0": "11-08-08"
    },
    {
      "0": "23-09-08"
    },
    {
      "0": "13-10-08"
    },
    {
      "0": "23-07-09"
    },
    {
      "0": "12-04-10"
    },
    {
      "0": "29-11-11"
    },
    {
      "0": "10-11-08"
    },
    {
      "0": "03-09-20"
    },
    {
      "0": "29-09-08"
    },
    {
      "0": "17-11-08"
    },
    {
      "0": "13-12-18"
    },
    {
      "0": "22-08-08"
    },
    {
      "0": "22-12-09"
    },
    {
      "0": "01-04-09"
    },
    {
      "0": "15-11-11"
    },
    {
      "0": "13-11-18"
    },
    {
      "0": "11-12-18"
    },
    {
      "0": "06-10-20"
    },
    {
      "0": "26-01-18"
    },
    {
      "0": "13-10-08"
    },
    {
      "0": "08-01-19"
    },
    {
      "0": "17-12-08"
    },
    {
      "0": "07-04-09"
    },
    {
      "0": "22-09-17"
    },
    {
      "0": "13-09-12"
    },
    {
      "0": "18-01-10"
    },
    {
      "0": "28-07-09"
    },
    {
      "0": "01-03-10"
    },
    {
      "0": "27-10-21"
    },
    {
      "0": "10-07-15"
    }
  ],
  "209B": [
    {
      "a": "acq",
      "x": "50"
    },
    {
      "a": "E00401082C414CA9",
      "x": "11"
    },
    {
      "a": "ACQ",
      "x": "50"
    },
    {
      "a": "alls",
      "x": "12"
    },
    {
      "a": "lbs1",
      "x": "12"
    },
    {
      "a": "F100",
      "x": "12"
    },
    {
      "a": "alma",
      "x": "12"
    },
    {
      "a": "alma",
      "x": "12"
    },
    {
      "a": "alma",
      "x": "12"
    },
    {
      "a": "koha",
      "x": "12"
    },
    {
      "a": "adis",
      "x": "12"
    },
    {
      "a": "adis",
      "x": "12"
    },
    {
      "a": "adis",
      "x": "12"
    },
    {
      "a": "koha",
      "x": "12"
    },
    {
      "a": "koha",
      "x": "12"
    },
    {
      "a": "koha",
      "x": "12"
    },
    {
      "a": "adis",
      "x": "12"
    },
    {
      "a": "adis",
      "x": "12"
    },
    {
      "a": "adis",
      "x": "12"
    }
  ],
  "209O": [
    {
      "a": "ea",
      "x": "00"
    },
    {
      "a": "ea",
      "x": "00"
    },
    {
      "a": "ex EXZ-16",
      "x": "00"
    },
    {
      "a": "ACQ",
      "x": "00"
    },
    {
      "a": "alma",
      "x": "00"
    }
  ],
  "220B": [
    {
      "a": "2009-01-27"
    },
    {
      "a": "ACQ"
    },
    {
      "a": "FB 450 CA-CK"
    },
    {
      "a": "Materialart: BU",
      "x": "00"
    },
    {
      "a": "Materialart: BU",
      "x": "00"
    },
    {
      "a": "2009/828"
    },
    {
      "a": "2018/155"
    },
    {
      "a": "snsb"
    },
    {
      "a": "jmjz"
    },
    {
      "a": "WP"
    },
    {
      "a": "AE"
    },
    {
      "a": "t1"
    },
    {
      "a": "29.09.08/wpt"
    },
    {
      "a": "ste; sc"
    },
    {
      "a": "boe"
    },
    {
      "a": "745/12"
    },
    {
      "a": "01.03.10/1"
    }
  ],
  "245Z": [
    {
      "9": "058046763",
      "V": "Tev",
      "a": "phi 270",
      "j": "Wörterbuch",
      "N": "<h3><A HREF=\"https://www.ub.uni-kiel.de/de/faecherkatalog/phi/index.html\">Systematischer Fächerkatalog Philosophie (phi)</A></h3>",
      "x": "50"
    },
    {
      "a": "Lal",
      "x": "00"
    },
    {
      "a": "HIA",
      "x": "00"
    },
    {
      "3": "226872157",
      "9": "1296872157",
      "V": "Tei",
      "a": "Phil 1a Met",
      "x": "00"
    },
    {
      "3": "228973775",
      "9": "1298973775",
      "V": "Tei",
      "a": "D 1 / Philosophie / Lexikon",
      "x": "00"
    },
    {
      "3": "227941071",
      "9": "1297941071",
      "V": "Tei",
      "a": "C 3",
      "j": "Philosophie (Einführungen)",
      "v": "kein FH-Standort; in FH bei C 1",
      "x": "00"
    },
    {
      "3": "316116181",
      "9": "1386116181",
      "V": "Tei",
      "a": "E 000",
      "x": "00"
    },
    {
      "a": "PHIL",
      "x": "00"
    }
  ],
  "237B": [
    {
      "a": " PHI 200810"
    },
    {
      "0": "2010",
      "a": "12-12-08"
    },
    {
      "0": "1809"
    },
    {
      "0": "00907"
    }
  ],
  "201D": [
    {
      "0": "0089:06-05-19"
    },
    {
      "0": "0035:14-06-19"
    },
    {
      "0": "TUUB:01-07-08"
    },
    {
      "0": "TUUB:22-09-08"
    },
    {
      "0": "FRUB:11-12-08"
    },
    {
      "0": "FR156:10-06-09"
    },
    {
      "0": "FR038:01-03-18"
    },
    {
      "0": "SBFH:13-11-09"
    },
    {
      "0": "SBUB:23-06-10"
    },
    {
      "0": "DDSU:11-12-08"
    },
    {
      "0": "KNUB:26-08-08"
    },
    {
      "0": "S1LB:29-09-08"
    },
    {
      "0": "MAUB:02-03-16"
    },
    {
      "0": "MAUB:02-03-16"
    },
    {
      "0": "MAUB:25-03-16"
    },
    {
      "0": "L1UB:11-08-08"
    },
    {
      "0": "HDUB:23-09-08"
    },
    {
      "0": "HDBSPI:13-10-08"
    },
    {
      "0": "HDBSJU:23-07-09"
    },
    {
      "0": "HDBSDE:12-04-10"
    },
    {
      "0": "HDBSIR:29-11-11"
    },
    {
      "0": "KAUB:10-11-08"
    },
    {
      "0": "S1U106:03-09-20"
    },
    {
      "0": "KALB:29-09-08"
    },
    {
      "0": "C1UB:17-11-08"
    },
    {
      "0": "ULUB:13-12-18"
    },
    {
      "0": "FR129:22-08-08"
    },
    {
      "0": "S2LGPH:22-12-09"
    },
    {
      "0": "S2SGPH:01-04-09"
    },
    {
      "0": "HDBSPH:15-11-11"
    },
    {
      "0": "G183:13-11-18"
    },
    {
      "0": "G160:11-12-18"
    },
    {
      "0": "G202:06-10-20"
    },
    {
      "0": "KAPH:26-01-18"
    },
    {
      "0": "FR026:13-10-08"
    },
    {
      "0": "HDBSFC:08-01-19"
    },
    {
      "0": "MAIS:17-12-08"
    },
    {
      "0": "MAIS:07-04-09"
    },
    {
      "0": "S1BA:22-09-17"
    },
    {
      "0": "FR160:13-09-12"
    },
    {
      "0": "ULHEZB:18-01-10"
    },
    {
      "0": "TUAUSP:28-07-09"
    },
    {
      "0": "KAMI:01-03-10"
    },
    {
      "0": "S2ESSE:27-10-21"
    },
    {
      "0": "B1DIPF:10-07-15"
    }
  ],
  "206X": [
    {
      "0": "23101014900003502"
    },
    {
      "0": "1138752478"
    },
    {
      "0": "2296675860002561"
    },
    {
      "0": "2296675930002561"
    },
    {
      "0": "22167409700002561"
    },
    {
      "0": "KAUB-319231"
    },
    {
      "0": "G183-3832"
    },
    {
      "0": "G160-5088"
    },
    {
      "0": "G202-2156"
    },
    {
      "0": "000035402"
    },
    {
      "0": "200340255"
    }
  ],
  "206W": [
    {
      "0": "0015584001"
    }
  ],
  "244Z": [
    {
      "a": "Gegenwart",
      "x": "00"
    },
    {
      "a": "Philosophie",
      "x": "01"
    },
    {
      "a": "Lexikon",
      "x": "02"
    },
    {
      "S": "s",
      "a": "Philosophie",
      "x": "00"
    },
    {
      "S": "s",
      "a": "Handbuch, Nachschlagewerk, Wörterbuch",
      "x": "00"
    },
    {
      "S": "f",
      "a": "Lehrbuch",
      "x": "01"
    },
    {
      "S": "s",
      "a": "Ethik",
      "x": "02"
    },
    {
      "S": "s",
      "a": "Philosophieunterricht",
      "x": "03"
    },
    {
      "S": "f",
      "a": "Wörterbuch",
      "x": "00"
    },
    {
      "S": "s",
      "a": "Philosophie",
      "x": "00"
    }
  ],
  "107F": [
    {
      "0": "1"
    }
  ],
  "203S": [
    {
      "0": "57482149X"
    },
    {
      "0": "580922367"
    },
    {
      "0": "587799080"
    },
    {
      "0": "602533295"
    },
    {
      "0": "1001217047"
    },
    {
      "0": "614732727"
    },
    {
      "0": "639277632"
    },
    {
      "0": "587806443"
    },
    {
      "0": "579204650"
    },
    {
      "0": "58150013X"
    },
    {
      "0": "578271540"
    },
    {
      "0": "581066839"
    },
    {
      "0": "582418283"
    },
    {
      "0": "606051619"
    },
    {
      "0": "631817085"
    },
    {
      "0": "696441462"
    },
    {
      "0": "581483715"
    },
    {
      "0": "585435170"
    },
    {
      "0": "1037966155"
    },
    {
      "0": "617878463"
    },
    {
      "0": "695143468"
    },
    {
      "0": "994164718"
    },
    {
      "0": "582393965"
    },
    {
      "0": "1039228933"
    },
    {
      "0": "588235644"
    },
    {
      "0": "597750289"
    },
    {
      "0": "981291430"
    },
    {
      "0": "722843380"
    },
    {
      "0": "621174688"
    },
    {
      "0": "606454373"
    },
    {
      "0": "626713153"
    },
    {
      "0": "857987917"
    }
  ],
  "247F": [
    {
      "a": "3",
      "x": "2"
    },
    {
      "a": "15/09/08",
      "x": "6"
    },
    {
      "a": "3",
      "x": "2"
    },
    {
      "a": "22/09/08",
      "x": "6"
    },
    {
      "a": "dbs:2",
      "x": "0"
    },
    {
      "a": "C.W.",
      "x": "2"
    }
  ],
  "245H": [
    {
      "a": "2"
    },
    {
      "a": "10"
    },
    {
      "a": "13"
    }
  ],
  "237A": [
    {
      "a": "1x HA 12"
    },
    {
      "a": "Inv.Nr. 22966/20"
    },
    {
      "a": "0109 ; rev"
    }
  ],
  "245X": [
    {
      "s": "2a"
    }
  ],
  "209R": [
    {
      "u": "http://deposit.d-nb.de/cgi-bin/dokserv?id=3111295&prov=M&dok_var=1&dok_ext=htm="
    }
  ]
}